CHANGES.rst
LICENSE
MANIFEST.in
README.md
infinity.py
setup.py
test_infinity.py
infinity.egg-info/PKG-INFO
infinity.egg-info/SOURCES.txt
infinity.egg-info/dependency_links.txt
infinity.egg-info/not-zip-safe
infinity.egg-info/requires.txt
infinity.egg-info/top_level.txt