Metadata-Version: 1.1
Name: infinity
Version: 1.1
Summary: All-in-one infinity value for Python. Can be compared to any object.
Home-page: https://github.com/kvesteri/infinity
Author: Konsta Vesterinen
Author-email: konsta@fastmonkeys.com
License: BSD
Platform: any
Classifier: Environment :: Web Environment
Classifier: Intended Audience :: Developers
Classifier: License :: OSI Approved :: BSD License
Classifier: Operating System :: OS Independent
Classifier: Programming Language :: Python
Classifier: Topic :: Internet :: WWW/HTTP :: Dynamic Content
Classifier: Topic :: Software Development :: Libraries :: Python Modules
